framechanger/__init__.py
framechanger/app.py
framechanger/icon.ico
framechanger/settings.json
framechanger/stylesheets.py
framechanger/wallpaper_changer.py
framechanger-1.2.0.dist-info/LICENSE.txt
framechanger-1.2.0.dist-info/METADATA
framechanger-1.2.0.dist-info/WHEEL
framechanger-1.2.0.dist-info/entry_points.txt
framechanger-1.2.0.dist-info/top_level.txt
framechanger-1.2.0.dist-info/RECORD
