Metadata-Version: 2.1
Name: framechanger
Version: 1.2.0
Summary: A wallpaper changer app that fetches images from TMDB
Home-page: https://github.com/SkyCreates/FrameChanger
Author: Akash Seam
Author-email: Akash Seam <akash.seam@gmail.com>
License: MIT
Project-URL: homepage, https://github.com/SkyCreates/FrameChanger
Project-URL: repository, https://github.com/SkyCreates/FrameChanger
Project-URL: documentation, https://github.com/SkyCreates/FrameChanger/wiki
Requires-Python: >=3.6
License-File: LICENSE.txt
Requires-Dist: requests
Requires-Dist: PyQt5
